LICENSE
README.md
setup.py
FireEye_AWS.egg-info/PKG-INFO
FireEye_AWS.egg-info/SOURCES.txt
FireEye_AWS.egg-info/dependency_links.txt
FireEye_AWS.egg-info/entry_points.txt
FireEye_AWS.egg-info/requires.txt
FireEye_AWS.egg-info/top_level.txt
fireeye/__init__.py
fireeye/__main__.py
fireeye/aws.py
fireeye/aws_lambda.py
fireeye/exceptions.py
fireeye/logger.py
fireeye/slack.py