Metadata-Version: 2.4
Name: FireEye-AWS
Version: 0.6.0.dev0
Summary: AWS Monitoring Toolkit
Author: Hardik Nanda
Author-email: hnanda21@gmail.com
License: Apache-2.0 License
Keywords: fireeye aws cloudwatch logs logs-insights
Classifier: Environment :: Console
Classifier: Operating System :: POSIX :: Linux
Classifier: Programming Language :: Python :: 3.11
Classifier: Development Status :: 1 - Planning
Classifier: Topic :: Software Development
Requires-Python: >=3.8
License-File: LICENSE
Requires-Dist: boto3==1.35.54
Requires-Dist: botocore==1.35.54
Requires-Dist: jmespath==1.0.1
Requires-Dist: python-dateutil==2.9.0.post0
Requires-Dist: s3transfer==0.10.3
Requires-Dist: six==1.16.0
Requires-Dist: urllib3==2.2.3
Dynamic: author
Dynamic: author-email
Dynamic: classifier
Dynamic: description
Dynamic: description-content-type
Dynamic: keywords
Dynamic: license
Dynamic: license-file
Dynamic: requires-dist
Dynamic: requires-python
Dynamic: summary
